setup.py
template_for_tea/__init__.py
template_for_tea/helloTea.py
template_for_tea.egg-info/PKG-INFO
template_for_tea.egg-info/SOURCES.txt
template_for_tea.egg-info/dependency_links.txt
template_for_tea.egg-info/top_level.txt