Metadata-Version: 2.1
Name: template-for-tea
Version: 1.0
Summary: Template for project TEA.xyz,your gateway towards blockchain and OSS
Home-page: https://github.com/eminentgu
Author: Eminent
Author-email: EminentGuXiang@protonmail.com
License: Apache 2.0
Keywords: template_for_tea
Classifier: Development Status :: 3 - Alpha
Classifier: Intended Audience :: Developers
Classifier: Programming Language :: Python :: 3
Classifier: Programming Language :: Python :: 3.7
Classifier: Programming Language :: Python :: 3.8
Classifier: Programming Language :: Python :: 3.9
Classifier: Programming Language :: Python :: 3.10
Classifier: Programming Language :: Python :: 3 :: Only
Classifier: License :: OSI Approved :: MIT License
Classifier: Operating System :: OS Independent
